sitkhi/__init__.py
sitkhi/display.py
sitkhi/interplate.py
sitkhi/io.py
sitkhi-1.0.2.dist-info/METADATA
sitkhi-1.0.2.dist-info/WHEEL
sitkhi-1.0.2.dist-info/top_level.txt
sitkhi-1.0.2.dist-info/RECORD
